cdcstream/__init__.py
cdcstream/cdcstream.py
cdcstream/dilca_wrapper.py
cdcstream/tools.py
cdcstream-0.2.3.dist-info/LICENSE
cdcstream-0.2.3.dist-info/METADATA
cdcstream-0.2.3.dist-info/WHEEL
cdcstream-0.2.3.dist-info/RECORD
