Metadata-Version: 2.1
Name: cdcstream
Version: 0.2.3
Summary: Implementation of Ienco's algorithm CDCStream
Home-page: https://github.com/fzi-forschungszentrum-informatik/cdcstream
License: GNU General Public License v3.0
Author: Martin Trat
Author-email: trat@fzi.de
Requires-Python: >=3.8
Classifier: Development Status :: 3 - Alpha
Classifier: License :: OSI Approved :: GNU General Public License v3 or later (GPLv3+)
Classifier: License :: Other/Proprietary License
Classifier: Programming Language :: Python :: 3
Classifier: Programming Language :: Python :: 3.8
Classifier: Programming Language :: Python :: 3.9
Classifier: Programming Language :: Python :: 3.10
Classifier: Programming Language :: Python :: 3.11
Classifier: Programming Language :: Python :: 3
Classifier: Topic :: Scientific/Engineering :: Artificial Intelligence
Requires-Dist: numpy
Requires-Dist: packaging
Requires-Dist: pandas
Requires-Dist: python-javabridge
Requires-Dist: python-weka-wrapper3 (>=0.2,<0.3)
Project-URL: Repository, https://github.com/fzi-forschungszentrum-informatik/cdcstream
